fiuai_sdk_agent/README.md
fiuai_sdk_agent/SETUP.md
fiuai_sdk_agent/__init__.py
fiuai_sdk_agent/agents/README.md
fiuai_sdk_agent/agents/__init__.py
fiuai_sdk_agent/agents/agent.py
fiuai_sdk_agent/agents/callbacks/__init__.py
fiuai_sdk_agent/agents/callbacks/agent_callback.py
fiuai_sdk_agent/agents/callbacks/debug_callback.py
fiuai_sdk_agent/agents/context/__init__.py
fiuai_sdk_agent/agents/context/context_manager.py
fiuai_sdk_agent/agents/context/types.py
fiuai_sdk_agent/agents/event/publish.py
fiuai_sdk_agent/agents/knowlege/__init__.py
fiuai_sdk_agent/agents/knowlege/instance.py
fiuai_sdk_agent/agents/plan/README.md
fiuai_sdk_agent/agents/plan/__init__.py
fiuai_sdk_agent/agents/plan/manager.py
fiuai_sdk_agent/agents/plan/new_plan.py
fiuai_sdk_agent/agents/prompts/__init__.py
fiuai_sdk_agent/agents/prompts/constraints.py
fiuai_sdk_agent/agents/prompts/doctype_prompt.py
fiuai_sdk_agent/agents/prompts/load.py
fiuai_sdk_agent/agents/prompts/user_prompt.py
fiuai_sdk_agent/agents/types/__init__.py
fiuai_sdk_agent/agents/types/agent_type.py
fiuai_sdk_agent/agents/types/data_type.py
fiuai_sdk_agent/agents/types/event_type.py
fiuai_sdk_agent/agents/types/intent_type.py
fiuai_sdk_agent/agents/types/knowledge_type.py
fiuai_sdk_agent/agents/types/plan_type.py
fiuai_sdk_agent/agents/types/state_type.py
fiuai_sdk_agent/pkg/__init__.py
fiuai_sdk_agent/pkg/http/__init__.py
fiuai_sdk_agent/pkg/http/client.py
fiuai_sdk_agent/pkg/llm/__init__.py
fiuai_sdk_agent/pkg/llm/error.py
fiuai_sdk_agent/pkg/llm/llm_config.py
fiuai_sdk_agent/pkg/llm/manager.py
fiuai_sdk_agent/pkg/llm/parser.py
fiuai_sdk_agent/pkg/llm/price_config.py
fiuai_sdk_agent/pkg/llm/settings.py
fiuai_sdk_agent/pkg/llm/types.py
fiuai_sdk_agent/pkg/llm/vendor.py
fiuai_sdk_agent/pkg/llm/callbacks/__init__.py
fiuai_sdk_agent/pkg/llm/callbacks/agent_callback.py
fiuai_sdk_agent/pkg/llm/callbacks/debug_callback.py
fiuai_sdk_agent/pkg/llm/callbacks/local_log_callback.py
fiuai_sdk_agent/pkg/llm/callbacks/utils/__init__.py
fiuai_sdk_agent-0.1.2.dist-info/METADATA
fiuai_sdk_agent-0.1.2.dist-info/WHEEL
fiuai_sdk_agent-0.1.2.dist-info/top_level.txt
fiuai_sdk_agent-0.1.2.dist-info/RECORD
