Metadata-Version: 2.4
Name: fiuai-sdk-agent
Version: 0.1.2
Summary: FiuAI SDK Agent - A framework for building AI agents with LLM support, context management, and event handling
Author-email: liming <lmlala@aliyun.com>
License: Proprietary
Keywords: ai,agent,llm,langchain,fiuai
Classifier: Development Status :: 3 - Alpha
Classifier: Intended Audience :: Developers
Classifier: Programming Language :: Python :: 3
Classifier: Programming Language :: Python :: 3.12
Classifier: Topic :: Software Development :: Libraries :: Python Modules
Requires-Python: >=3.12
Requires-Dist: fiuai-sdk-python>=0.6.5
Requires-Dist: langchain>=1.2.0
Requires-Dist: langchain-openai>=1.1.6
Requires-Dist: langchain-core>=1.2.0
Requires-Dist: pydantic>=2.0.0
Requires-Dist: pydantic-settings>=2.0.0
Requires-Dist: redis>=7.1.0
Requires-Dist: httpx>=0.27.0
Requires-Dist: tenacity>=8.0.0
Requires-Dist: snowflake-id>=1.0.2
Requires-Dist: jinja2==3.1.6
Requires-Dist: markupsafe==3.0.3
Provides-Extra: dev
Requires-Dist: pytest>=7.0.0; extra == "dev"
Requires-Dist: pytest-asyncio>=0.21.0; extra == "dev"
Requires-Dist: black>=23.0.0; extra == "dev"
Requires-Dist: ruff>=0.1.0; extra == "dev"
